giskard_hub/__init__.py
giskard_hub/_base_client.py
giskard_hub/_evaluation.py
giskard_hub/client.py
giskard_hub/errors.py
giskard_hub/data/__init__.py
giskard_hub/data/_base.py
giskard_hub/data/_entity.py
giskard_hub/data/chat.py
giskard_hub/data/chat_test_case.py
giskard_hub/data/check.py
giskard_hub/data/dataset.py
giskard_hub/data/evaluation.py
giskard_hub/data/knowledge_base.py
giskard_hub/data/model.py
giskard_hub/data/project.py
giskard_hub/data/scheduled_evaluation.py
giskard_hub/data/task.py
giskard_hub/resources/__init__.py
giskard_hub/resources/_resource.py
giskard_hub/resources/_utils.py
giskard_hub/resources/chat_test_cases.py
giskard_hub/resources/checks.py
giskard_hub/resources/datasets.py
giskard_hub/resources/evaluations.py
giskard_hub/resources/knowledge_bases.py
giskard_hub/resources/models.py
giskard_hub/resources/projects.py
giskard_hub/resources/scheduled_evaluations.py
giskard_hub-2.0.1.dist-info/METADATA
giskard_hub-2.0.1.dist-info/WHEEL
giskard_hub-2.0.1.dist-info/licenses/LICENSE
giskard_hub-2.0.1.dist-info/RECORD
