Metadata-Version: 2.4
Name: giskard-hub
Version: 2.0.1
Summary: The giskard_hub library allows you to interact with the Giskard Hub, a platform that centralizes the validation process of LLM applications, empowering product teams to ensure all functional, business & legal requirements are met, and keeping them in close contact with the development team to avoid delayed deployment timelines.
Project-URL: Homepage, https://github.com/Giskard-AI/giskard-hub
Project-URL: Repository, https://github.com/Giskard-AI/giskard-hub
Project-URL: Documentation, https://docs.giskard.ai/
Author-email: Giskard Team <hello@giskard.ai>
License-File: LICENSE
Requires-Python: <4.0,>=3.10
Requires-Dist: httpx<1,>=0.27.0
Requires-Dist: python-dateutil>=2.9.0.post0
Requires-Dist: rich>=13.7.1
